{
  "We're excited you're here.": "Wir freuen uns, dass Sie hier sind.",
  "Welcome to": "Willkommen bei {{App_Name}}!",
  "Show on launch": "Beim Start anzeigen",
  "Ready to connect to your server?": "Bist du bereit dich mit deinem Server zu verbinden?",
  "Language": "Sprache",
  "Collect Anonymous Data": "Sammeln Sie anonyme Daten",
  "Allow us to collect anonymous data to improve our app": "Erlauben Sie uns, anonyme Daten zu sammeln, um unsere App zu verbessern",
  "How do you intend to use sFTP Client:": "Wie beabsichtigen Sie, den sFTP-Client zu verwenden:",
  "Your choice below may entitle you to a discount.": "Ihre Wahl unten berechtigt Sie zu einem Rabatt.",
  "Are you a startup business?": "Bist du ein Startup-Unternehmen?",
  "No": "Nein",
  "Yes": "Ja",
  "i.e. founded within the past 3 years": "dh gegründet in den letzten 3 Jahren",
  "Year Founded?": "Gründungsjahr?",
  "Are you any of the following listed below": "Haben Sie eine der folgenden Möglichkeiten?",
  "None Listed Below": "Keine unten aufgeführt",
  "Non-Profit Organisation / Charity": "Non-Profit-Organisation / Wohltätigkeit",
  "Student (High School, College, University)": "Student (Gymnasium, Universität, Universität)",
  "Teacher of an Educational Institution": "Lehrer einer Bildungseinrichtung",
  "Continue": "Fortsetzen",
  "Need Website Hosting?": "Brauchen Sie Website-Hosting?",
  "Take a look at plans below provided by our partner": "Sehen Sie sich untenstehende Pläne unseres Partners an",
  "View": "Aussicht",
  "No Thanks!": "Nein Danke!",
  "Getting Started": "Anfangen",
  "Select an option below to help get you started.": "Wählen Sie unten eine Option, um Ihnen den Einstieg zu erleichtern.",
  "Login": "Anmeldung",
  "Already registered?": "Bereits registriert?",
  "login to your account": "Melde dich in deinem Konto an",
  "Register an Account": "Einen Account registrieren",
  "Manage License Keys, Share Data and more...": "Lizenzschlüssel verwalten, Daten teilen und mehr ...",
  "Create a Connection": "Erstellen Sie eine Verbindung",
  "Start by creating your first connection": "Beginnen Sie mit der Erstellung Ihrer ersten Verbindung",
  "Import Data": "Daten importieren",
  "Import existing data from": "Importieren Sie vorhandene Daten aus",
  "Close": "Schließen",
  "Community": "Gemeinschaft",
  "Help / Support": "Hilfe Unterstützung",
  "About": "Über",
  "Licenses": "Lizenzen",
  "Documentation": "Dokumentation",
  "Change Log": "Änderungsprotokoll",
  "FAQ's": "FAQs",
  "Blog": "Blog",
  "My Account": "Mein Konto",
  "Account": "Konto",
  "Forename": "Vorname",
  "Surname": "Nachname",
  "Email Address": "E-Mail-Addresse",
  "Job Title": "Berufsbezeichnung",
  "Loading": "Wird geladen",
  "Update Details": "Details aktualisieren",
  "Advertisements": "Werbung",
  "Upgrade": "Aktualisierung",
  "File Permissions": "Dateiberechtigungen",
  "Owner Permissions": "Besitzer Berechtigungen",
  "Group Permissions": "Gruppenberechtigungen",
  "Public Permissions": "Öffentliche Berechtigungen",
  "Read": "Lesen",
  "Write": "Schreiben",
  "Execute": "Ausführen",
  "Value": "Wert",
  "Cancel": "Stornieren",
  "Okay": "okay",
  "New": "Neu",
  "Edit": "Bearbeiten",
  "Diagnostic Tool": "Diagnosehilfsmittel",
  "General": "Allgemeines",
  "Diagnostic Name": "Diagnostischer Name",
  "Name": "Name",
  "CHANGE": "VERÄNDERUNG",
  "Domain / URL": "Domäne / URL",
  "Enter your domain": "Geben Sie Ihre Domain ein",
  "Enter your domain or IP address": "Geben Sie Ihre Domain oder IP-Adresse ein",
  "Add Diagnostic Tool": "Diagnosewerkzeug hinzufügen",
  "Update Diagnostic Tool": "Diagnose-Tool aktualisieren",
  "Connection": "Verbindung",
  "Connection Name": "Verbindungsname",
  "Host": "Gastgeber",
  "Port": "Hafen",
  "Typically 21 or 22": "In der Regel 21 oder 22",
  "Connection Type": "Verbindungstyp",
  "Logon Type": "Anmeldungsart",
  "Username": "Nutzername",
  "Password": "Passwort",
  "Passphrase for Key File": "Passphrase für Schlüsseldatei",
  "optional": "wahlweise",
  "Key File": "Schlüsseldatei",
  "Select a Key File": "Wählen Sie eine Schlüsseldatei",
  "Select": "Wählen",
  "Add Connection": "Verbindung hinzufügen",
  "Update Connection": "Verbindung aktualisieren",
  "Advanced": "Fortgeschritten",
  "Default Local Directory": "Standardmäßiges lokales Verzeichnis",
  "Select a local directory": "Wählen Sie ein lokales Verzeichnis",
  "Defaults to desktop": "Standardmäßig auf Desktop",
  "Default Remote Directory": "Standard-Remote-Verzeichnis",
  "Leave blank for the server to decide": "Leer lassen, damit der Server entscheidet",
  "Simultaneous Transfer Limit": "Simultanes Übertragungslimit",
  "Synchronized Browsing": "Synchronisiertes Browsen",
  "Notes": "Anmerkungen",
  "Note down anything you need to remember": "Notieren Sie alles, was Sie sich merken müssen",
  "If you sync your connections these notes will be encrypted": "Wenn Sie Ihre Verbindungen synchronisieren, werden diese Notizen verschlüsselt",
  "Default transfer limit is [st] for [ct]": "Standardübertragungslimit ist {{simultane_transfers}} für {{conn_type}}",
  "Fingerprint": "Fingerabdruck",
  "Remember": "Merken",
  "Manage License Key": "Lizenzschlüssel verwalten",
  "Details": "Einzelheiten",
  "An error occurred!": "Ein Fehler ist aufgetreten!",
  "Key": "Schlüssel",
  "Type": "Art",
  "Device": "Gerät",
  "Devices": "Geräte",
  "active": "aktiv",
  "suspended": "suspendiert",
  "in-active": "inaktiv",
  "terminated": "beendet",
  "Activate": "aktivieren Sie",
  "Deactivate": "Deaktivieren",
  "License Keys": "Lizenzschlüssel",
  "License Key": "Lizenzschlüssel",
  "Status": "Status",
  "Manage": "Verwalten",
  "No License Keys Found!": "Keine Lizenzschlüssel gefunden!",
  "You don't currently have any license keys, you'll need to purchase one before you can activate this device.": "Sie haben derzeit keine Lizenzschlüssel, Sie müssen einen erwerben, bevor Sie dieses Gerät aktivieren können.",
  "Login Invalid": "Anmeldung ungültig",
  "Incorrect details provided": "Falsche Angaben zur Verfügung gestellt",
  "Valid password length": "Gültige Passwortlänge",
  "Minimum 8 characters required": "Mindestens 8 Zeichen erforderlich",
  "Enter a valid email": "Geben Sie eine * gültige * E-Mail-Adresse ein",
  "Valid email format": "Gültiges E-Mail-Format",
  "Please enter the email you registered with": "Bitte geben Sie die E-Mail ein, mit der Sie sich registriert haben",
  "Minimum 8 characters": "Mindestens 8 Zeichen",
  "Monitor Name": "Name überwachen",
  "Monitor Type": "Bildschirmtyp",
  "Add Monitor": "Monitor hinzufügen",
  "Update Monitor": "Aktualisieren Sie den Monitor",
  "Preferences": "Einstellungen",
  "Something went wrong!": "Etwas ist schief gelaufen!",
  "Sorry something didn't go quite right, please try again later.": "Tut mir leid, dass etwas nicht ganz richtig gelaufen ist, bitte versuche es später noch einmal.",
  "Confirm Password": "Bestätige das Passwort",
  "Register": "Registrieren",
  "Valid": "Gültig",
  "Enter your forename": "Geben Sie Ihren Vornamen ein",
  "Enter your surname": "Geben Sie Ihren Nachnamen ein",
  "Must be 2 or more characters": "Muss 2 oder mehr Zeichen enthalten",
  "Passwords Match": "Passwörter stimmen überein",
  "Passwords do not match!": "Passwörter stimmen nicht überein!",
  "Re-enter your password again": "Geben Sie Ihr Passwort erneut ein",
  "Valid email required for validation": "Gültige E-Mail zur Validierung erforderlich",
  "Your trial version has expired!": "Ihre Testversion ist abgelaufen!",
  "Upgrade to Pro": "Upgrade auf Pro",
  "Buy Now": "Kaufe jetzt",
  "Purchase your license key directly from our website or find out more information about our Pro Version.": "Erwerben Sie Ihren Lizenzschlüssel direkt von unserer Website oder erfahren Sie mehr über unsere Pro Version.",
  "Once payment is complete, you'll need to login below so you can activate your license, if you don't already have an account one will be created for you with a temporary password.": "Sobald die Zahlung abgeschlossen ist, müssen Sie sich unten einloggen, damit Sie Ihre Lizenz aktivieren können. Wenn Sie noch kein Konto haben, wird ein Konto für Sie mit einem temporären Passwort erstellt.",
  "Once payment is complete, you'll need to activate your license.": "Sobald die Zahlung abgeschlossen ist, müssen Sie Ihre Lizenz aktivieren.",
  "A new window has been opened in your browser!": "Ein neues Fenster wurde in Ihrem Browser geöffnet!",
  "Purchase sFTP Client Pro directly from the Mac App Store.": "Erwerben Sie sFTP Client Pro direkt aus dem Mac App Store.",
  "Your trial has expired!": "Ihre Probezeit ist vorbei!",
  "Please purchase a license to continue!": "Bitte erwerben Sie eine Lizenz, um fortzufahren!",
  "user": "Benutzer",
  "User": "Nutzer",
  "Purchase your license key directly from our website.": "Erwerben Sie Ihren Lizenzschlüssel direkt von unserer Website.",
  "TRIAL STATUS": "Teststatus",
  "Expired": "Abgelaufen",
  "Benefits": "Leistungen",
  "License": "Lizenz",
  "Payment Method": "Bezahlverfahren",
  "Once payment is complete, you'll need to login below so you can activate your license.": "Sobald die Zahlung abgeschlossen ist, müssen Sie sich unten einloggen, damit Sie Ihre Lizenz aktivieren können.",
  "(If you don't currently have an account one will be created for you with a temporary password)": "(Wenn Sie noch kein Konto haben, wird eines mit einem temporären Passwort für Sie erstellt)",
  "Go Back": "Geh zurück",
  "Lite": "Lite",
  "Premier": "Premier",
  "Business": "Geschäft",
  "Unlimited": "Unbegrenzt",
  "Commercial": "Kommerziell",
  "All businesses / enterprises (including partnerships and sole traders)": "Alle Unternehmen / Unternehmen (einschließlich Partnerschaften und Einzelunternehmer)",
  "Non-Commercial": "Nicht kommerziell",
  "Home users, freelancers, non-profit organisations or educational institutions": "Heimanwender, Freiberufler, Non-Profit-Organisationen oder Bildungseinrichtungen",
  "HDD": "HDD",
  "Bandwidth": "Bandbreite",
  "Domains": "Domänen",
  "File Not Supported": "Datei wird nicht unterstützt",
  "Must be of type": "Muss vom Typ sein",
  "Ask for Password": "Fragen Sie nach dem Passwort",
  "Normal": "Normal",
  "Anonymous": "Anonym",
  "Standard File Transfer (FTP)": "Standard-Dateiübertragung (FTP)",
  "Explicit SSL File Transfer (FTPS)": "Explizite SSL-Dateiübertragung (FTPS)",
  "Implicit SSL File Transfer (FTPS)": "Implizite SSL-Dateiübertragung (FTPS)",
  "Secure File Transfer (SFTP)": "Sicherer Dateitransfer (SFTP)",
  "SSH Terminal": "SSH-Terminal",
  "You need to select a default local directory": "Sie müssen ein standardmäßiges lokales Verzeichnis auswählen",
  "Above Local / Remote View (Default)": "Oberhalb der lokalen / Remote-Ansicht (Standard)",
  "Main Tab - Next to File Transfer": "Main Tab - Neben der Dateiübertragung",
  "Tab within Transfer Queue": "Registerkarte innerhalb der Übertragungswarteschlange",
  "Aqua Blue": "Wasserblau",
  "Emerald Green": "Smaragdgrün",
  "Cupcake Pink": "Cupcake Pink",
  "Midnight Purple": "Mitternacht Purpur",
  "Ruby Red": "Rubinrot",
  "Sunset Orange": "Sonnenuntergang Orange",
  "This shows the initial welcome screen allowing you to quickly access the more important areas of sFTP Client, you can also disable this from the Getting Started screen.": "Dies zeigt den Begrüßungsbildschirm, mit dem Sie schnell auf die wichtigeren Bereiche des sFTP-Clients zugreifen können. Sie können dies auch über den Bildschirm Erste Schritte deaktivieren.",
  "Layout": "Layout",
  "Transfer Log": "Übertragungsprotokoll",
  "Decide where you want the transfer logs to appear.": "Entscheiden Sie, wo die Übertragungsprotokolle angezeigt werden sollen.",
  "Local / Remote Directories": "Lokale / Remote-Verzeichnisse",
  "This option will swap the local / remote directory panels (so remote will show on the left, whilst local shows on the right)": "Diese Option vertauscht die lokalen / Remote-Verzeichnis-Panels (so wird Remote auf der linken Seite angezeigt, während lokale Shows auf der rechten Seite)",
  "Swap Sides": "Seiten tauschen",
  "Transfers": "Transfers",
  "Max Simultaneous Transfers (FTP, FTPIS, FTPES)": "Max. Gleichzeitige Übertragungen (FTP, FTPIS, FTPES)",
  "Majority of FTP servers only support 2": "Die meisten FTP-Server unterstützen nur 2",
  "Max Simultaneous Transfers (SFTP / SSH)": "Max. Gleichzeitige Übertragung (SFTP / SSH)",
  "Check your server configs for the true max limit": "Überprüfen Sie Ihre Serverkonfigurationen auf das tatsächliche maximale Limit",
  "Max Transfer Attempts": "Max Transferversuche",
  "Specify amount of time to keep re-trying a transfer before considering it as failed": "Geben Sie den Zeitraum an, nach dem eine Übertragung erneut versucht werden soll, bevor sie als fehlgeschlagen betrachtet wird",
  "Themes": "Themen",
  "Theme Colour": "Thema Farbe",
  "Light Theme": "Leichtes Thema",
  "Default": "Standard",
  "Dark Theme": "Dunkles Thema",
  "If you have any suggestions for themes please let us know.": "Wenn Sie Vorschläge für Themen haben, lassen Sie es uns bitte wissen.",
  "Data": "Daten",
  "Importing data from [type]!": "Importieren von Daten aus {{imp_type}}!",
  "[type] imported successfully!": "{{imp_type}} erfolgreich importiert!",
  "Exporting data!": "Daten exportieren!",
  "Data was successfully exported!": "Daten wurden erfolgreich exportiert!",
  "Import": "Einführen",
  "Export Data": "Daten exportieren",
  "Backup your data for later use": "Sichern Sie Ihre Daten für die spätere Verwendung",
  "Connections": "Verbindungen",
  "Monitoring": "Überwachung",
  "Monitor": "Monitor",
  "Diagnostic Tools": "Diagnosewerkzeuge",
  "Diagnostic": "Diagnose",
  "Note": "Hinweis",
  "Any private keys will be removed and any saved passwords will be encoded.": "Alle privaten Schlüssel werden entfernt und gespeicherte Passwörter werden verschlüsselt.",
  "Trial Time Remaining": "Noch verbleibende Probezeit",
  "SYNCING": "SYNCHRONISIERUNG",
  "SYNC": "SYNC",
  "IN SYNC": "SYNCHRON",
  "off": "aus",
  "File Transfer": "Datei Übertragung",
  "Connection Log": "Verbindungsprotokoll",
  "Port Forwarding": "Port-Weiterleitung",
  "Compare Directories": "Verzeichnisse vergleichen",
  "Toggle Sync Browsing": "Wechseln Sie das Sync-Browsing",
  "Show/Hide Log": "Protokoll ein- / ausblenden",
  "Show/Hide Transfers": "Ein- / Ausblenden von Übertragungen",
  "Show/Hide Local Folder List": "Lokale Ordnerliste ein- / ausblenden",
  "Show/Hide Remote Folder List": "Remote-Ordnerliste ein- / ausblenden",
  "Save": "sparen",
  "Loading File": "Datei wird geladen",
  "File Opened": "Datei geöffnet",
  "Error opening file": "Fehler beim Öffnen der Datei",
  "Saving!": "Speichern!",
  "Error writing file": "Fehler beim Schreiben der Datei",
  "Saved": "Gerettet",
  "Confirm Host Key": "Bestätigen Sie den Hostschlüssel",
  "Permissions Error": "Berechtigungen Fehler",
  "Error scanning directories": "Fehler beim Durchsuchen der Verzeichnisse",
  "Error": "Error",
  "Will not overwrite": "Überschreibt nicht",
  "File Rename Error": "Datei umbenennen Fehler",
  "Permission denied": "Erlaubnis verweigert",
  "New File": "Neue Datei",
  "Filename": "Dateiname",
  "File Created": "Datei erstellt",
  "New File Error": "Neuer Dateifehler",
  "New Folder": "Neuer Ordner",
  "Folder Name": "Ordnernamen",
  "New Folder Error": "Neuer Ordnerfehler",
  "Error uploading watched file": "Fehler beim Hochladen der überwachten Datei",
  "Error watching file": "Fehler beim Ansehen der Datei",
  "Confirm Delete": "Löschen bestätigen",
  "Are you sure you want to delete the selected files / folders?": "Möchten Sie die ausgewählten Dateien / Ordner wirklich löschen?",
  "Deleting local files": "Lokale Dateien löschen",
  "Deleting Remote Files": "Löschen von Remote-Dateien",
  "Overwrite File": "Datei überschreiben",
  "Unlicensed": "Nicht lizenziert",
  "Account Settings": "Account Einstellungen",
  "Manage License Keys": "Lizenzschlüssel verwalten",
  "Manage Team": "Team verwalten",
  "Logout": "Ausloggen",
  "Please enter more than 10 characters to submit your feedback": "Bitte geben Sie mehr als 10 Zeichen ein, um Ihr Feedback zu senden",
  "Thank You! Your feedback has been submitted successfully.": "Danke! Ihr Feedback wurde erfolgreich übermittelt.",
  "Latest Information": "Neueste Informationen",
  "Loading latest information": "Neueste Informationen laden",
  "Error loading latest information!": "Fehler beim Laden der letzten Informationen!",
  "Now Available!": "Jetzt verfügbar!",
  "Download": "Herunterladen",
  "read more": "Weiterlesen",
  "Feedback": "Feedback",
  "Your feedback is important to us, please use the form below to let us know how we're doing or let us know your idea's, suggestions, or any issues you're having.": "Ihr Feedback ist uns wichtig. Bitte verwenden Sie das unten stehende Formular, um uns mitzuteilen, wie es uns geht, oder teilen Sie uns Ihre Ideen, Vorschläge oder Probleme mit.",
  "Submit Feedback": "Feedback senden",
  "Service Checks": "Serviceüberprüfungen",
  "Website / Blog": "Webseite / Blog",
  "API": "API",
  "Forums": "Foren",
  "New Connection": "Neue Verbindung",
  "New Monitor": "Neuer Monitor",
  "New Diagnostic": "Neue Diagnose",
  "Coming Soon!": "Demnächst!",
  "Sorry! This is not yet available": "Es tut uns leid! Dies ist noch nicht verfügbar",
  "Copy": "Kopieren",
  "Paste": "Einfügen",
  "Total": "Gesamt",
  "Folder": "Mappe",
  "Search Connections": "Verbindungen suchen",
  "Search Diagnostic Tools": "Suche Diagnose-Tools",
  "Search Monitors": "Suchmonitore",
  "You haven't created any folders or saved any [manager]'s yet.": "Sie haben noch keine Ordner erstellt oder einen {{mnrr_name}} gespeichert.",
  "This folder is currently empty, add some folders or save your favourite [manager]'s here.": "Dieser Ordner ist momentan leer, füge einige Ordner hinzu oder speichere deinen Favoriten {{mnrr_name}} hier.",
  "Save Connection": "Verbindung speichern",
  "Local Address": "Lokale Adresse",
  "Local Port": "Lokaler Hafen",
  "Remote Address": "Entfernte Adresse",
  "Remote Port": "Remote-Port",
  "Auto Start": "Auto-Start",
  "Manual Start": "Manueller Start",
  "Stopped": "Gestoppt",
  "Starting": "Beginnend",
  "Started": "Gestartet",
  "Connection Error": "Verbindungsfehler",
  "Forward Out": "Vorwärts aus",
  "Add Forward": "Vorwärts hinzufügen",
  "Forward": "Nach vorne",
  "Start": "Anfang",
  "Stop": "Halt",
  "Delete": "Löschen",
  "Forward In": "Vorwärts In",
  "No Items Selected!": "Keine Artikel ausgewählt!",
  "You must select items before you can perform this action.": "Sie müssen Elemente auswählen, bevor Sie diese Aktion ausführen können.",
  "Files": "Dateien",
  "Folders": "Ordner",
  "Total Folders": "Gesamtzahl der Ordner",
  "Size": "Größe",
  "Total Files": "Gesamtzahl der Dateien",
  "Selected": "Ausgewählt",
  "Upload": "Hochladen",
  "Open": "Öffnen",
  "Rename": "Umbenennen",
  "Edit File": "Datei bearbeiten",
  "Permissions": "Berechtigungen",
  "Create New File": "Erstellen Sie eine neue Datei",
  "Create New Folder": "Neuen Ordner erstellen",
  "Refresh": "Aktualisierung",
  "total size": "Gesamtgröße",
  "folder": "Mappe",
  "folders": "Ordner",
  "file": "Datei",
  "files": "Dateien",
  "Connect": "Verbinden",
  "Source": "Quelle",
  "Direction": "Richtung",
  "Destination": "Ziel",
  "Priority": "Priorität",
  "Remaining": "Verbleibend",
  "Speed": "Geschwindigkeit",
  "Progress": "Fortschritt",
  "Failed": "Gescheitert",
  "Reason": "Grund",
  "Completed": "Abgeschlossen",
  "Reprocess Selected": "Ausgewählte erneut verarbeiten",
  "Clear Selected": "Auswahl löschen",
  "Reprocess All": "Alle erneut verarbeiten",
  "Clear All": "Alles löschen",
  "Pause Selected": "Auswahl anhalten",
  "Resume Selected": "Ausgewählt fortsetzen",
  "Cancel Selected": "Ausgewählte löschen",
  "Pause All": "Alles pausieren",
  "Resume All": "Alles fortsetzen",
  "Cancel All": "Alle Absagen",
  "Queued": "In Warteschlange",
  "Failed Transfers": "Fehlgeschlagene Transfers",
  "Completed Transfers": "Abgeschlossene Transfers",
  "Message Log": "Nachrichtenprotokoll",
  "Last Modified": "Zuletzt bearbeitet",
  "Owner / Group": "Besitzer / Gruppe",
  "Ensure you have your local directory and remote directory set to the same project path in order for this to work effectively, you may also want to enable the Compare Local / Remote Directories feature.": "Stellen Sie sicher, dass Ihr lokales Verzeichnis und Ihr Remote-Verzeichnis auf denselben Projektpfad eingestellt sind, damit dies effektiv funktioniert. Sie sollten auch die Funktion Local / Remote-Verzeichnisse vergleichen aktivieren.",
  "Compare Local / Remote Directories": "Vergleichen Sie lokale / Remote-Verzeichnisse",
  "See which local files / folders require uploading or remote files / folders require downloading. This option works well with Synchronized Browsing.": "Sehen Sie, welche lokalen Dateien / Ordner hochgeladen werden müssen oder ob entfernte Dateien / Ordner heruntergeladen werden müssen. Diese Option funktioniert gut mit Synchronized Browsing.",
  "Sync Connections": "Verbindungen synchronisieren",
  "Sync Connection": "Verbindung synchronisieren",
  "Sync connection with your account or disable to only have this connection available on this device. We use Diffie Hellman Elliptic Curve encryption for all sensitive data using a public / private key combination that's only available to your account.": "Synchronisieren Sie die Verbindung mit Ihrem Konto oder deaktivieren Sie, dass nur diese Verbindung auf diesem Gerät verfügbar ist. Wir verwenden die Diffie Hellman Elliptic Curve-Verschlüsselung für alle sensiblen Daten unter Verwendung einer öffentlichen / privaten Tastenkombination, die nur für Ihr Konto verfügbar ist.",
  "Preserve Log": "Protokoll beibehalten",
  "Store all connection logs locally and show all history within the connection log window.": "Speichern Sie alle Verbindungsprotokolle lokal und zeigen Sie den gesamten Verlauf im Verbindungsprotokollfenster an.",
  "Enable": "Aktivieren",
  "Enabled": "aktiviert",
  "This displays information, actions, errors and success messages to and from the server in which you are connected to.": "Dies zeigt Informationen, Aktionen, Fehler und Erfolgsmeldungen an und von dem Server an, mit dem Sie verbunden sind.",
  "Transfer Queue": "Übertragungswarteschlange",
  "This displays the queued files / folders waiting to transfer, as well as the files / folders that have either failed or completed to transfer.": "Hier werden die in der Warteschlange befindlichen Dateien / Ordner, die auf die Übertragung warten, sowie die Dateien / Ordner angezeigt, deren Übertragung entweder fehlgeschlagen oder abgeschlossen ist.",
  "Local Directory Treeview": "Lokale Verzeichnisbaumansicht",
  "This displays your local directory view in a treeview structure, starting from your root path up to the folder your currently active in.": "Dadurch wird Ihre lokale Verzeichnisansicht in einer Baumstruktur angezeigt, beginnend mit Ihrem Stammpfad bis zu dem Ordner, in dem Sie gerade aktiv sind.",
  "Remote Directory Treeview": "Remoteverzeichnis-Baumansicht",
  "This displays your servers directory view in a treeview structure, starting from your root path up to the folder your currently active in.": "Dies zeigt die Server-Verzeichnisansicht in einer Baumstruktur an, beginnend mit Ihrem Stammpfad bis zu dem Ordner, in dem Sie gerade aktiv sind.",
  "Show": "Show",
  "Hide": "verbergen",
  "Recover Account": "Account wiederherstellen",
  "Recover": "Genesen",
  "Any data that has been synced to your account will be lost.": "Alle Daten, die mit Ihrem Konto synchronisiert wurden, gehen verloren.",
  "New Password": "Neues Kennwort",
  "Choose File": "Datei wählen",
  "WARNING": "WARNUNG",
  "Settings": "die Einstellungen",
  "Share": "Aktie",
  "Edit Directory Path": "Bearbeiten Sie den Verzeichnispfad",
  "Directory": "Verzeichnis",
  "Local Filesystem": "Lokales Dateisystem",
  "Response": "Antwort",
  "Command": "Befehl",
  "Local": "Lokal",
  "Server": "Server",
  "Change Password": "Passwort ändern",
  "Confirm New Password": "Bestätige neues Passwort",
  "Current Password": "Aktuelles Passwort",
  "Enter your existing password": "Gib dein bestehendes Passwort ein",
  "Password has been successfully updated": "Das Passwort wurde erfolgreich aktualisiert",
  "Current password did not match": "Das aktuelle Passwort stimmt nicht überein",
  "Latest Information / Feedback": "Neueste Informationen / Feedback",
  "This option will show / hide the right side information / feedback tabs displayed on the manager": "Mit dieser Option werden die auf dem Manager angezeigten Informationen / Feedback-Registerkarten angezeigt",
  "Login / Register": "Anmeldung Registrieren",
  "You need to login / register to use this feature.": "Sie müssen sich anmelden / registrieren, um diese Funktion nutzen zu können.",
  "Search": "Suche",
  "Sorry": "Es tut uns leid",
  "No Results Found": "Keine Ergebnisse gefunden",
  "Searching": "Suche",
  "Revoke": "Widerrufen",
  "Assigned to": "Zugewiesen an",
  "Owner": "Inhaber",
  "Search Account": "Konto suchen",
  "Remove Assignee": "Entfernen Sie den Zuständigen",
  "Are you sure you want to remove this assignee?": "Möchten Sie diesen Bevollmächtigten wirklich entfernen?",
  "Search Email": "Suche Email",
  "Ensure the user has updated their profile to be searchable": "Stellen Sie sicher, dass der Benutzer sein Profil aktualisiert hat, damit es durchsucht werden kann",
  "No Devices Found!": "Keine Geräte gefunden!",
  "No devices have yet been activated on this license.": "Für diese Lizenz wurden noch keine Geräte aktiviert.",
  "Searchable": "Durchsuchbar",
  "Allow other users to search for you by email": "Erlauben Sie anderen Nutzern, per E-Mail nach Ihnen zu suchen",
  "You need to contact us to change your email": "Sie müssen uns kontaktieren, um Ihre E-Mail zu ändern",
  "Account updated!": "Konto aktualisiert!",
  "Domain / Record": "Domäne / Datensatz",
  "Select a Record": "Wählen Sie einen Datensatz",
  "Trace Route": "Ablaufverfolgung",
  "Port Check": "Portprüfung",
  "Whois Lookup": "Whois Nachschlagen",
  "Tool Type": "Werkzeugtyp",
  "Shows additional log data to help debug connection issues": "Zeigt zusätzliche Protokolldaten an, um Verbindungsprobleme zu beheben",
  "Debug": "Debuggen",
  "Debug Log": "Austestungsprotokoll",
  "This displays your treeview in a side by side view instead of above and below view.": "Dies zeigt Ihre Baumansicht in einer nebeneinander liegenden Ansicht anstelle von oben und unten an.",
  "Vertical Treeview": "Vertikale Baumansicht",
  "Horizontal": "Horizontal",
  "Vertical": "Vertikale"
}
