{
  "We're excited you're here.": "Kei te hari matou kei konei koe.",
  "Welcome to": "Nau mai ki {{app_name}}!",
  "Show on launch": "Whakaatuhia i te whakarewatanga",
  "Ready to connect to your server?": "Kua rite ki te hono atu ki to tūmau?",
  "Language": "Reo",
  "Collect Anonymous Data": "Kohia Raraunga Anonymous",
  "Allow us to collect anonymous data to improve our app": "Tukua mai ki a matou ki te kohikohi i nga raraunga haupae ki te whakapai i to taatau taupānga",
  "How do you intend to use sFTP Client:": "Me pehea koe ki te whakamahi i te Kiritaki sFTP:",
  "Your choice below may entitle you to a discount.": "Ko to whiringa i raro nei ka whakaaetia koe ki te utu.",
  "Are you a startup business?": "He pakihi whakaoho koe?",
  "No": "No",
  "Yes": "Ae",
  "i.e. founded within the past 3 years": "i te mea i whakaturia i roto i nga tau 3 kua pahure",
  "Year Founded?": "Kua whakaturia te Tau?",
  "Are you any of the following listed below": "Kei a koe tetahi o nga mea e whai ake nei i raro nei",
  "None Listed Below": "Karekau i Whakaritea i raro nei",
  "Non-Profit Organisation / Charity": "Ko te Whakaawe-kore-Moni / Haapaarai",
  "Student (High School, College, University)": "Ākonga (Kura Tuarua, Kura Tuarua, Whare Wānanga)",
  "Teacher of an Educational Institution": "Kaiako o te Whare Whakaakoranga",
  "Continue": "Haere tonu",
  "Need Website Hosting?": "E hiahia ana te manaaki paetukutuku?",
  "Take a look at plans below provided by our partner": "Tirohia nga mahere i raro i to maatau hoa",
  "View": "Tiro",
  "No Thanks!": "Karekau he mihi!",
  "Getting Started": "Tīmatahia",
  "Select an option below to help get you started.": "Tīpakohia he kōwhiringa i raro nei hei āwhina kia tīmata koe.",
  "Login": "Whakauru",
  "Already registered?": "Kua rēhitatia?",
  "login to your account": "takiuru ki tō pūkete",
  "Register an Account": "Tuhia he Kaute",
  "Manage License Keys, Share Data and more...": "Whakahaerehia nga Paerewa Raihana, Tiri Raraunga me te ake ...",
  "Create a Connection": "Waihanga Hononga",
  "Start by creating your first connection": "Tīmata ma te hanga i to hononga tuatahi",
  "Import Data": "Kawemai Raraunga",
  "Import existing data from": "Kawemai i nga raraunga o teianei",
  "Close": "Katia",
  "Community": "Te hapori",
  "Help / Support": "Āwhina &amp; Tautoko",
  "About": "Mō",
  "Licenses": "Raihana",
  "Documentation": "Tuhinga",
  "Change Log": "Huria te Waka",
  "FAQ's": "FAQ",
  "Blog": "Blog",
  "My Account": "Taku Pūkete",
  "Account": "Pūkete",
  "Forename": "Ingoa o mua",
  "Surname": "Te ingoa ingoa",
  "Email Address": "Wāhitau Īmēra",
  "Job Title": "Taitara Job",
  "Loading": "Whakamahia",
  "Update Details": "Whakahōu Whakatauranga",
  "Advertisements": "Ngā Pānuitanga",
  "Upgrade": "Whakapai ake",
  "File Permissions": "Whakaaetanga Kōnae",
  "Owner Permissions": "Whakaaetanga Tika",
  "Group Permissions": "Whakaaetanga Rōpū",
  "Public Permissions": "Whakaaetanga Katoa",
  "Read": "Pānuihia",
  "Write": "Tuhia",
  "Execute": "Whakarite",
  "Value": "Uara",
  "Cancel": "Whakakore",
  "Okay": "Pai",
  "New": "New",
  "Edit": "Whakatika",
  "Diagnostic Tool": "Rauemi Diagnostic",
  "General": "General",
  "Diagnostic Name": "Ingoa Tuhituhi",
  "Name": "Ingoa",
  "CHANGE": "Tuhinga",
  "Domain / URL": "Domain / URL",
  "Enter your domain": "E tomo i to rohe",
  "Enter your domain or IP address": "E tomo i to rohe rohe IP ranei",
  "Add Diagnostic Tool": "Tāpirihia te Tohu Hangarau",
  "Update Diagnostic Tool": "Whakahōuhia te Tool Diagnostic",
  "Connection": "Hononga",
  "Connection Name": "Ingoa Hononga",
  "Host": "Kaihautū",
  "Port": "Tauranga",
  "Typically 21 or 22": "Tikanga 21, 22 ranei",
  "Connection Type": "Momo Hononga",
  "Logon Type": "Momo takiuru",
  "Username": "Ingoa Kaiwhakamahi",
  "Password": "Kupuhipa",
  "Passphrase for Key File": "Kupuhipa mo te Kōnae Matua",
  "optional": "kōwhiringa",
  "Key File": "Kōnae Matua",
  "Select a Key File": "Tīpakohia he Kōnae Matua",
  "Select": "Tīpako",
  "Add Connection": "Tāpiri Hononga",
  "Update Connection": "Whakahōu Hononga",
  "Advanced": "Arā atu",
  "Default Local Directory": "Taitara Whaiaronga Taunoa",
  "Select a local directory": "Tīpakohia he whaiaronga rohe",
  "Defaults to desktop": "Taunoa ki te papamahi",
  "Default Remote Directory": "Rarangi Mamao Taunoa",
  "Leave blank for the server to decide": "Waiho kia kore e taea e te tūmau te whakatau",
  "Simultaneous Transfer Limit": "Whakawhitinga Whakawhitinga Kotahi",
  "Synchronized Browsing": "Aroturuki Tukutahi",
  "Notes": "Tuhipoka",
  "Note down anything you need to remember": "Tuhia tetahi mea e hiahia ana koe ki te mahara",
  "If you sync your connections these notes will be encrypted": "Mena ka tukutahi koe i enei hononga, ka hunahia enei tuhinga",
  "Default transfer limit is [st] for [ct]": "Ko te rohe whakawhitinga taunoa ko {{simultaneous_transfers}} mo {{conn_type}}",
  "Fingerprint": "Pukupuku",
  "Remember": "Kia mahara",
  "Manage License Key": "Whakahaerehia te Paerewa Raihana",
  "Details": "Nga taipitopito",
  "An error occurred!": "Kua puta he hapa!",
  "Key": "Kī",
  "Type": "Momo",
  "Device": "Pūrere",
  "Devices": "Pūrere",
  "active": "kaha",
  "suspended": "whakamutua",
  "in-active": "kei te kaha",
  "terminated": "mutu",
  "Activate": "Whakahohe",
  "Deactivate": "Whakamutua",
  "License Keys": "Papa Raihana",
  "License Key": "Raihana Raihana",
  "Status": "Tūnga",
  "Manage": "Whakahaere",
  "No License Keys Found!": "Karekau he Kee Raihana i kitea!",
  "You don't currently have any license keys, you'll need to purchase one before you can activate this device.": "Kaore he raihana raihana kei a koe i tenei wa, ka hiahia koe ki te hoko i mua i te wa e taea ai e koe te whakahohe i tenei taputapu.",
  "Login Invalid": "Whakauru Invalid",
  "Incorrect details provided": "He tika nga korero i whakaratohia",
  "Valid password length": "Te roa o te kupuhipa",
  "Minimum 8 characters required": "E hiahiatia ana nga tohu mo te 8",
  "Enter a valid email": "Tāurutia he * whaimana * īmēra",
  "Valid email format": "He hōputu īmēra pai",
  "Please enter the email you registered with": "Tēnā koa whakauruhia te īmēra kua rēhitahia koe",
  "Minimum 8 characters": "Ko nga tohu iti 8",
  "Monitor Name": "Ingoa Aroturuki",
  "Monitor Type": "Kaupapa Aroturuki",
  "Add Monitor": "Tāpiri Aroturuki",
  "Update Monitor": "Whakahōu Aroturuki",
  "Preferences": "Nga manakohanga",
  "Something went wrong!": "Kua he tetahi mea!",
  "Sorry something didn't go quite right, please try again later.": "Aroha mai ki tetahi mea kaore i tika tika, whakamatauhia ano i muri mai.",
  "Confirm Password": "Whakaae Kupuhipa",
  "Register": "Rēhita",
  "Valid": "He pai",
  "Enter your forename": "Tomohia to ingoa",
  "Enter your surname": "Tomohia to ingoa",
  "Must be 2 or more characters": "Kia rua neke atu ranei nga horopaki",
  "Passwords Match": "Kupuhipa Kuputuhi",
  "Passwords do not match!": "Kaore nga kupuhipa e ōrite!",
  "Re-enter your password again": "Whakauru anō i tō kupuhipa",
  "Valid email required for validation": "He īmēra pai e hiahiatia ana mo te whakamana",
  "Your trial version has expired!": "Kua pau te putanga whakamatautau!",
  "Upgrade to Pro": "Whakapai ake ki Pro",
  "Buy Now": "Hokona Na",
  "Purchase your license key directly from our website or find out more information about our Pro Version.": "Hokona tō kī raihana i tō mātou pae tukutuku, ka kitea rānei ētahi atu mōhiohio e pā ana ki to Putanga Pro.",
  "Once payment is complete, you'll need to login below so you can activate your license, if you don't already have an account one will be created for you with a temporary password.": "Kia oti te utu, me whakauru koe ki raro kia taea ai e koe te whakahohe i to raihana, mehemea kaore he keehi ka hangahia mo koe ma te kupuhipa poto.",
  "Once payment is complete, you'll need to activate your license.": "Kia oti te utu, ka hiahia koe ki te whakahohe i to raihana.",
  "A new window has been opened in your browser!": "Kua whakatuwheratia he matapihi hou ki to rorohiko!",
  "Purchase sFTP Client Pro directly from the Mac App Store.": "Ko te hokohoko sFTP Cl mai i te Mac App Store.",
  "Your trial has expired!": "Kua pau to whakamatautau!",
  "Please purchase a license to continue!": "Hokona he raihana hei haere tonu!",
  "user": "kaiwhakamahi",
  "User": "Kaiwhakamahi",
  "Purchase your license key directly from our website.": "Hokona tō kī raihana i tō mātou paetukutuku.",
  "TRIAL STATUS": "Tuhinga o mua",
  "Expired": "Kua mutu",
  "Benefits": "Hua",
  "License": "Raihana",
  "Payment Method": "Tikanga Moni",
  "Once payment is complete, you'll need to login below so you can activate your license.": "Kia oti te utu, me whakauru koe ki raro kia taea ai e koe te whakahohe i to raihana.",
  "(If you don't currently have an account one will be created for you with a temporary password)": "(Ki te kore koe e whai korero i tetahi wa ka hangahia mo koe me te kupuhipa poto)",
  "Go Back": "Haere Hoki",
  "Lite": "Putanga",
  "Premier": "Pirimia",
  "Business": "Pakihi",
  "Unlimited": "Unlimited",
  "Commercial": "Pakihi",
  "All businesses / enterprises (including partnerships and sole traders)": "Nga pakihi katoa / hinonga (tae atu ki nga hoahoa me nga kaihokohoko kotahi)",
  "Non-Commercial": "Nga Kaihoko-kore",
  "Home users, freelancers, non-profit organisations or educational institutions": "Nga kaiwhakamahi whare, nga kaitautoko, nga umanga kore-pai, nga umanga ako",
  "HDD": "HDD",
  "Bandwidth": "Tuhinga o mua",
  "Domains": "Nga puni",
  "File Not Supported": "Kōnae Kāore i Tautokohia",
  "Must be of type": "Me te momo",
  "Ask for Password": "Inoi mo te Kupuhipa",
  "Normal": "Te tikanga",
  "Anonymous": "Anonymous",
  "Standard File Transfer (FTP)": "Whakawhiti Kōnae Paerewa (FTP)",
  "Explicit SSL File Transfer (FTPS)": "Whakawhiti Kōnae SSL Tiwhikete (FTPS)",
  "Implicit SSL File Transfer (FTPS)": "Whakawhiti Kōnae SSL Tiwhikete (FTPS)",
  "Secure File Transfer (SFTP)": "Whakaaetanga Haumaru Haumaru (SFTP)",
  "SSH Terminal": "SSH Terminal",
  "You need to select a default local directory": "Me whiriwhiri koe i te whaiaronga taunoa taunoa",
  "Above Local / Remote View (Default)": "I runga ake i te Tirohanga Motu / Mamao (Taunoa)",
  "Main Tab - Next to File Transfer": "Tapapa Main - I muri ki te Whakawhiti Kōnae",
  "Tab within Transfer Queue": "Tapapa i roto i te Whakawhiti Tuutoko",
  "Aqua Blue": "Aqua Blue",
  "Emerald Green": "Emerald Green",
  "Cupcake Pink": "Te Pink Cupcake",
  "Midnight Purple": "Maapiri Tuarua",
  "Ruby Red": "Ruby Red",
  "Sunset Orange": "Sunset Orange",
  "This shows the initial welcome screen allowing you to quickly access the more important areas of sFTP Client, you can also disable this from the Getting Started screen.": "E whakaatu ana tenei i te maapatatanga tuatahi e taea ai e koe te uru wawe ki nga waahanga nui atu o te Kiritaki sFTP, ka taea hoki e koe te whakakore i tenei mai i te Mataara Whakamata.",
  "Layout": "Tahora",
  "Transfer Log": "Whakauru Whakawhiti",
  "Decide where you want the transfer logs to appear.": "Whakaotihia te wahi e hiahia ana koe kia puta mai nga rarangi whakawhiti.",
  "Local / Remote Directories": "Nga Kaitatau A-rohe / Mamao",
  "This option will swap the local / remote directory panels (so remote will show on the left, whilst local shows on the right)": "Ka whakakorehia e tenei kōwhiringa nga panui whaiaro / takiwāhi (ka whakaatu te tawhiti i te taha mauī, i te taha matau o te rohe)",
  "Swap Sides": "Nga Aukati",
  "Transfers": "Nga whakawhiti",
  "Max Simultaneous Transfers (FTP, FTPIS, FTPES)": "Ko nga Whakawhiti Whakaterenga Max (FTP, FTPIS, FTPES)",
  "Majority of FTP servers only support 2": "Ko te nuinga o nga kaiwhakarato FTP e tautoko ana i te 2",
  "Max Simultaneous Transfers (SFTP / SSH)": "Ko nga whakawhitinga Motuhake Max (SFTP / SSH)",
  "Check your server configs for the true max limit": "Tirohia o tautuhinga kaiwhakarato mo te tawhito mii pono",
  "Max Transfer Attempts": "Nga Whakataunga Whakawhiti Max",
  "Specify amount of time to keep re-trying a transfer before considering it as failed": "Tautuhia te nui o te wa ki te whakahou ano i te whakawhitinga i mua i te whakaaro o te mea i rahua",
  "Themes": "Kaupapa",
  "Theme Colour": "Tae Kaupapa",
  "Light Theme": "Kaupapa Marama",
  "Default": "Taunoa",
  "Dark Theme": "Kaupapa pouri",
  "If you have any suggestions for themes please let us know.": "Mena kei a koe etahi whakaaro mo nga kaupapa, me mohio mai.",
  "Data": "Raraunga",
  "Importing data from [type]!": "Kawemai i nga raraunga mai i {{imp_type}}!",
  "[type] imported successfully!": "{import_type}} kawemai i te pai!",
  "Exporting data!": "Te kaweake raraunga!",
  "Data was successfully exported!": "I huakina te raraunga!",
  "Import": "Kawemai",
  "Export Data": "Kaweake Raraunga",
  "Backup your data for later use": "Hokihia ō raraunga hei whakamahi i muri",
  "Connections": "Hononga",
  "Monitoring": "Te aroturuki",
  "Monitor": "Aroturuki",
  "Diagnostic Tools": "Ngā Utauta Tauira",
  "Diagnostic": "Te taatai",
  "Note": "Tuhipoka",
  "Any private keys will be removed and any saved passwords will be encoded.": "Ka whakakorea nga taviri whaiaro me nga kupuhipa ka tiakina.",
  "Trial Time Remaining": "Te wa e whakamatautau ana",
  "SYNCING": "Tuhinga",
  "SYNC": "SYNC",
  "IN SYNC": "IN SYNC",
  "off": "atu",
  "File Transfer": "Whakawhiti Kōnae",
  "Connection Log": "Hononga Hononga",
  "Port Forwarding": "Te Whakawhiti Poto",
  "Compare Directories": "Whakatauritehia nga Whakatauranga",
  "Toggle Sync Browsing": "Takahuri Takahuri Tukutahi",
  "Show/Hide Log": "Whakaatu / Hunahia te Waka",
  "Show/Hide Transfers": "Whakaatu / Huna Nga Whakawhiti",
  "Show/Hide Local Folder List": "Whakaatu / Huna Rārangi Kōpaki Rohe",
  "Show/Hide Remote Folder List": "Whakaatu / Hunahia te Rārangi Kōpaki Mamao",
  "Save": "Tiaki",
  "Loading File": "Ko te Whakaaetanga Kōnae",
  "File Opened": "Kua iritihia te Puka",
  "Error opening file": "Hapa whakatuwhera kōnae",
  "Saving!": "Tiakina!",
  "Error writing file": "Hapa tuhi tuhituhi",
  "Saved": "Tiakina",
  "Confirm Host Key": "Whakaatuhia te Key Host",
  "Permissions Error": "Hapa Whakaae",
  "Error scanning directories": "Hapa tirotiro i nga papaaata",
  "Error": "Hapa",
  "Will not overwrite": "Kaore e tuhirua",
  "File Rename Error": "Hapa Hapa Whakaingoa",
  "Permission denied": "Ka whakakorehia te whakaaetanga",
  "New File": "Kōnae Hōu",
  "Filename": "Ingoa Ingoa",
  "File Created": "I hangaia te Kōnae",
  "New File Error": "Hapa Kōnae Hōu",
  "New Folder": "Kōpaki Hōu",
  "Folder Name": "Ingoa Kōpaki",
  "New Folder Error": "Hapa Kōpaki Hōu",
  "Error uploading watched file": "Hapa te tuku ake i te kōnae tirotiro",
  "Error watching file": "Hapa te tiro i te kōnae",
  "Confirm Delete": "Whakaae Muku",
  "Are you sure you want to delete the selected files / folders?": "Kei te hiahia koe kia mukua nga kōnae / nga kōpaki kua tīpakohia?",
  "Deleting local files": "Muku i nga kōnae rohe",
  "Deleting Remote Files": "Muku i nga Kōnae Mamao",
  "Overwrite File": "Tuhia te Kōnae",
  "Unlicensed": "Kaore i te raihana",
  "Account Settings": "Tautuhinga Pūkete",
  "Manage License Keys": "Whakahaerehia nga Paerewa Raihana",
  "Manage Team": "Whakahaere Team",
  "Logout": "Whakaaturanga",
  "Please enter more than 10 characters to submit your feedback": "Tēnā koa tomo atu ki te 10 ngā pūāhua hei tuku i ō urupare",
  "Thank You! Your feedback has been submitted successfully.": "Mauruuru! Kua tukuna tō urupare ki a koe.",
  "Latest Information": "Nga Korero Hou",
  "Loading latest information": "Te whakamahi i nga korero hou",
  "Error loading latest information!": "Hapa kei te kawe i nga korero hou!",
  "Now Available!": "Kei te wātea!",
  "Download": "Tikiake",
  "read more": "pānuitia atu",
  "Feedback": "Whakaaro",
  "Your feedback is important to us, please use the form below to let us know how we're doing or let us know your idea's, suggestions, or any issues you're having.": "He mea nui to urupare ki a mätou, koa koa ki te whakamahi i te puka i raro nei hei whakamohio mai ki a mätau kei te mahi, kei te whakamohio ranei mätau ki ö whakaaro, whakaaro, he take ranei kei a koe.",
  "Submit Feedback": "Tukuna Whakautu",
  "Service Checks": "Ratonga Ratonga",
  "Website / Blog": "Paetukutuku / Blog",
  "API": "API",
  "Forums": "Nga Huihuinga",
  "New Connection": "Hononga Hou",
  "New Monitor": "Te Aroturuki Hou",
  "New Diagnostic": "New Diagnostic",
  "Coming Soon!": "Haere mai ana!",
  "Sorry! This is not yet available": "Aroha! Kāore i te wātea tonu tēnei",
  "Copy": "Tārua",
  "Paste": "Whakapiri",
  "Total": "Te tapeke",
  "Folder": "Kōpaki",
  "Search Connections": "Rapu Rapu",
  "Search Diagnostic Tools": "Rapua Ngā Utauta Tauira",
  "Search Monitors": "Rapu Rapu",
  "You haven't created any folders or saved any [manager]'s yet.": "Kāore i hangahia e koe tetahi kōpaki, kua tiakina rānei tetahi {{mngr_name}}.",
  "This folder is currently empty, add some folders or save your favourite [manager]'s here.": "Kei te ngaro tenei kōpaki, tāpirihia ētahi kōpaki ka tiakina tō {{mngr_name}} tino pai.",
  "Save Connection": "Tiakina te Hononga",
  "Local Address": "Wāhitau Paetata",
  "Local Port": "Tauranga Taone",
  "Remote Address": "Wāhitau Mamao",
  "Remote Port": "Tauranga Mamao",
  "Auto Start": "Tīmata Aunoa",
  "Manual Start": "Tīmata Tohu",
  "Stopped": "Kua mutu",
  "Starting": "Tīmata",
  "Started": "Kua tīmata",
  "Connection Error": "Hapa Hononga",
  "Forward Out": "Haere i waho",
  "Add Forward": "Tāpiri Whakamua",
  "Forward": "Tuhinga",
  "Start": "Tīmata",
  "Stop": "Kati",
  "Delete": "Mukua",
  "Forward In": "Haere Ki roto",
  "No Items Selected!": "Kāore he Tahua i Tīpakohia!",
  "You must select items before you can perform this action.": "Me whiriwhiri koe i nga mea i mua i te wa e taea ai e koe tenei mahi.",
  "Files": "Kōnae",
  "Folders": "Ngā Kōpaki",
  "Total Folders": "Ngā Kōpaki Tae",
  "Size": "Rahi",
  "Total Files": "Rauemi Tae",
  "Selected": "Kua tīpakohia",
  "Upload": "Tukuake",
  "Open": "Tuwhera",
  "Rename": "Whakaingoatia",
  "Edit File": "Whakatika Kōnae",
  "Permissions": "Whakaaetanga",
  "Create New File": "Waihanga Kōnae Hōu",
  "Create New Folder": "Waihanga Kōpaki Hōu",
  "Refresh": "Whakahou",
  "total size": "te rahi o te rahi",
  "folder": "kōpaki",
  "folders": "nga kōpaki",
  "file": "kōnae",
  "files": "kōnae",
  "Connect": "Hono",
  "Source": "Puna",
  "Direction": "Whakahaere",
  "Destination": "Tae",
  "Priority": "Tuhinga",
  "Remaining": "Te noho",
  "Speed": "Tere",
  "Progress": "Te ahunga whakamua",
  "Failed": "I rahua",
  "Reason": "Take",
  "Completed": "Kua oti",
  "Reprocess Selected": "Ko te whakawaha kua tohua",
  "Clear Selected": "Mukua Kua Tīpakohia",
  "Reprocess All": "Ko te Whakamutunga",
  "Clear All": "Mukua katoatia",
  "Pause Selected": "Paatu Kua Tīpakohia",
  "Resume Selected": "Kua tīpakohia te Tīpakonga",
  "Cancel Selected": "Whakakorehia Kua Tīpakohia",
  "Pause All": "Kati te katoa",
  "Resume All": "Whakahokia te katoa",
  "Cancel All": "Whakakore katoa",
  "Queued": "Kuini",
  "Failed Transfers": "Nga Whakawhiti Whakamutunga",
  "Completed Transfers": "Nga whakawhiti kua oti",
  "Message Log": "Waea Karere",
  "Last Modified": "Whakamutunga Whakamutunga",
  "Owner / Group": "Kaihoko / Rōpū",
  "Ensure you have your local directory and remote directory set to the same project path in order for this to work effectively, you may also want to enable the Compare Local / Remote Directories feature.": "Me mohio kei a koe te whaiaronga o to rohe me te whaiaronga mamao ki te huarahi kaupapa kotahi kia pai ai te mahi, ka hiahia pea koe ki te whakahoahoa i nga Whakatauranga Rohe / Mamao Mamao.",
  "Compare Local / Remote Directories": "Whakatauritehia nga Whakatauranga A-rohe / Mamao",
  "See which local files / folders require uploading or remote files / folders require downloading. This option works well with Synchronized Browsing.": "Tirohia nga kōnae / putea o te takiwa e hiahia ana kia tikiakehia nga kōnae / putea mamao ranei. Kei te pai tenei kōwhiringa ki te Tirotiro Tukutahi.",
  "Sync Connections": "Nga Hononga Tukutahi",
  "Sync Connection": "Hononga Tukutahi",
  "Sync connection with your account or disable to only have this connection available on this device. We use Diffie Hellman Elliptic Curve encryption for all sensitive data using a public / private key combination that's only available to your account.": "Whakaritea te hononga ki taau kaute, ka mono ranei ki te whakauru i tenei hononga i runga i tenei taputapu. Ka whakamahi tatou i te whakamunatanga Evetihana Hiko o te Diffie Hellman e pa ana ki nga raraunga taiao katoa e whakamahi ana i te huinga matua / tūmataiti motuhake e wātea noa ana ki tō pūkete.",
  "Preserve Log": "Tiakina te Waka",
  "Store all connection logs locally and show all history within the connection log window.": "Tiakina nga rarangi hononga katoa i te rohe me te whakaatu i nga hitori katoa i roto i te matapihi takiuru hononga.",
  "Enable": "Whakahohea",
  "Enabled": "Kua whakahohe",
  "This displays information, actions, errors and success messages to and from the server in which you are connected to.": "Kei te whakaatu tenei i nga korero, nga mahi, nga hapa me nga karere angitu ki a mai i te tūmau e hono ana koe ki.",
  "Transfer Queue": "Whakaerenga Whakawhiti",
  "This displays the queued files / folders waiting to transfer, as well as the files / folders that have either failed or completed to transfer.": "E whakaatu ana tenei i nga kōnae / kōpaki kua tatarihia e tatari ana ki te whakawhiti, me nga kōnae / kōpaki kua oti, kua oti ranei te whakawhiti.",
  "Local Directory Treeview": "Local Directory Treeview",
  "This displays your local directory view in a treeview structure, starting from your root path up to the folder your currently active in.": "Ka whakaatu tenei i to tirohanga whaiaronga a-rohe i roto i te hanganga tirohanga rakau, timata mai i to ara pakiaka tae noa atu ki te putea e mahi ana koe inaianei.",
  "Remote Directory Treeview": "Rarangi Whaimana Directory",
  "This displays your servers directory view in a treeview structure, starting from your root path up to the folder your currently active in.": "Ka whakaatu tenei i to tirohanga whaiaronga ki te hanganga rakau, timata mai i to ara pakiaka tae noa atu ki te kōpaki kei a koe i tenei wa.",
  "Show": "Whakaatu",
  "Hide": "Huna",
  "Recover Account": "Whakaora Pūkete",
  "Recover": "Whakaora",
  "Any data that has been synced to your account will be lost.": "Ka ngaro nga raraunga kua tukuna ki to taakete.",
  "New Password": "Kupuhipa Hou",
  "Choose File": "Kōwhiria Kōnae",
  "WARNING": "WARNING",
  "Settings": "Tautuhinga",
  "Share": "Vahevahe",
  "Edit Directory Path": "Whakatikahia te Ara Whaiaronga",
  "Directory": "Whaiaronga",
  "Local Filesystem": "Pūnaha Kōnae Rohe",
  "Response": "Whakautu",
  "Command": "Whakahau",
  "Local": "Paetata",
  "Server": "Tūmau",
  "Change Password": "Hurihia te Kupuhipa",
  "Confirm New Password": "Whakaae Kupuhipa Hou",
  "Current Password": "Kupuhipa onāianei",
  "Enter your existing password": "Tomohia to kupuhipa kei roto",
  "Password has been successfully updated": "Kua pai te whakahou i te kupuhipa",
  "Current password did not match": "Kāore te kupuhipa o nāianei i te ōrite",
  "Latest Information / Feedback": "Nga Korero Hou / Whakaaro",
  "This option will show / hide the right side information / feedback tabs displayed on the manager": "Ka whakaatuhia e tenei kōwhiringa / huna i nga taapiri tuakiri matau / taapiri whakautu i whakaaturia ki te kaiwhakahaere",
  "Login / Register": "Takiuru / Rēhita",
  "You need to login / register to use this feature.": "Me takiuru / rēhita kia whakamahia tēnei āhuatanga.",
  "Search": "Rapua",
  "Sorry": "Aroha mai",
  "No Results Found": "Kāore he Hua i kitea",
  "Searching": "Te rapu",
  "Revoke": "Whakakore",
  "Assigned to": "Kua tohua ki",
  "Owner": "Kaipupuri",
  "Search Account": "Rapu Rapu",
  "Remove Assignee": "Tangohia te Kaihauturu",
  "Are you sure you want to remove this assignee?": "Kei te hiahia koe kia tango i tenei kaiwhakahaere?",
  "Search Email": "Rapu Īmēra",
  "Ensure the user has updated their profile to be searchable": "Me whakarite kua whakahoutia e te kaiwhakamahi o raatau tohu kia taea ai te rapu",
  "No Devices Found!": "Kāore he Pūrere i kitea!",
  "No devices have yet been activated on this license.": "Kaore i te whakahohehia he whakaaro ki tenei raihana.",
  "Searchable": "Ka taea te rapu",
  "Allow other users to search for you by email": "Tukua etahi atu kaiwhakamahi ki te rapu i a koe ma te īmēra",
  "You need to contact us to change your email": "Me whakawhiti mai koe ki a maatau ki te huri i to īmēra",
  "Account updated!": "Kua whakahouhia te kaute!",
  "Domain / Record": "Nga Rohe / Tuhituhi",
  "Select a Record": "Tīpakohia he Tuhi",
  "Trace Route": "Ara Rawa",
  "Port Check": "Tirohanga Pouaka",
  "Whois Lookup": "Ko wai e rapu",
  "Tool Type": "Momo Rauemi",
  "Shows additional log data to help debug connection issues": "Whakaatuhia ai etahi atu raraunga takiuru hei awhina i nga raru hononga",
  "Debug": "Pupuri",
  "Debug Log": "Debug Log",
  "This displays your treeview in a side by side view instead of above and below view.": "Ka whakaatu tenei i to tirohanga tirohanga ki tetahi taha taha taha taha kaore i runga ake nei.",
  "Vertical Treeview": "Porowhita Poutū",
  "Horizontal": "Whakapae",
  "Vertical": "Poutū"
}
